{
  "browser": {
    "headless": false,
    "slow_mo_ms": 80,
    "default_timeout_ms": 120000,
    "channel": "msedge",
    "use_persistent_profile": true,
    "use_system_chrome": false,
    "browser_mode": "dedicated",
    "user_data_dir": "ups_browser_profile"
  },
  "ups": {
    "home_url": "https://www.ups.com/us/en/home",
    "login_url": "https://www.ups.com/lasso/login?loc=en_US&returnto=https%3A%2F%2Fwww.ups.com%2Fus%2Fen%2Fhome",
    "batch_landing_url": "https://www.ups.com/us/en/shipping/batch-file-shipping",
    "username": "${UPS_USERNAME}",
    "password": "${UPS_PASSWORD}"
  },
  "lane": "depot",
  "lanes": {
    "depot": {
      "ship_from": {
        "company": "HomeDepot.com",
        "contact": "Cornerstone Products Group"
      },
      "payment": {
        "third_party_account": "1YA668",
        "third_party_zip": "30339",
        "third_party_country": "United States"
      }
    },
    "thdso": {
      "ship_from": {
        "company": "HomeDepot.com",
        "contact": "Cornerstone Products Group"
      },
      "payment": {
        "third_party_account": "1YA668",
        "third_party_zip": "30339",
        "third_party_country": "United States"
      }
    },
    "tractor": {
      "ship_from": {
        "company": "TractorSupply",
        "contact": "Cornerstone Products Group"
      },
      "payment": {
        "third_party_account": "87W6A8",
        "third_party_zip": "37027",
        "third_party_country": "United States"
      }
    }
  },
  "ship_from": {
    "company": "HomeDepot.com",
    "contact": "Cornerstone Products Group"
  },
  "payment": {
    "third_party_account": "1YA668",
    "third_party_zip": "30339",
    "third_party_country": "United States",
    "billing_account_label": "186Y47 - Worldship"
  },
  "selectors": {
    "header_login": "a:has(span.text:text-is('Log In')), button:has(span.text:text-is('Log In')), a:has-text('Log In')",
    "dropdown_login": "a:has(span.text:text-is('Log In')), button:has(span.text:text-is('Log In'))",
    "username_input": "#username, input[name='username']",
    "password_input": "#password, input[name='password']",
    "login_continue": "button:has-text('Continue'), button._button-login-id, button._button-login-password",
    "verify_success": ".success-circle, circle.success-circle, text=Success!",
    "shipping_tab": "button[aria-controls='subsection-shipping'], button:has-text('Shipping')",
    "batch_file_shipping": "a:has-text('Batch File Shipping'), span:has-text('Batch File Shipping')",
    "ship_now": "a:has-text('Ship Now'), button:has-text('Ship Now')",
    "browse_file": "#uploadFileButton, button:has-text('Browse for File')",
    "file_input": "input[type='file']",
    "my_addresses_dropdown": "select.ups-dropdown:has(option:text-is('My Default Address'))",
    "ship_from_edit": "span:has-text('Edit'), a:has-text('Edit')",
    "company_name": "#origin-cac_companyOrName",
    "contact_name": "#origin-cac_contactName",
    "email": "#origin-cac_email",
    "address_line1": "#origin-cac_addressLine1",
    "city": "#origin-cac_city",
    "state": "#origin-cac_state",
    "zip": "#origin-cac_postalCode",
    "bill_other_account": "label[for='bill-someone-else-tile'], text=Bill Other Account",
    "third_party_account": "#nbsPaymentAccountThirdPartyAccountNumberInput",
    "third_party_zip": "#nbsPaymentAccountThirdPartyPostalCodeInput",
    "third_party_country": "#nbsPaymentAccountCountryDropdownThirdParty",
    "billing_account": "label:has-text('186Y47'), label[for='billMyAccountSection0']",
    "preview_batch": "button:has-text('Preview Batch')",
    "process_all": "#nwsCartProcessAll, button:has-text('Process All')",
    "app_teaser_close": ".enhanced-app-teaser-wrapper button[aria-label='Close'], .teaser-card-1 button[aria-label='Close'], button:has-text('No thanks'), button:has-text('Not now')",
    "cookie_close": "#onetrust-close-btn-container button, button.onetrust-close-btn-handler, button[aria-label='Close']",
    "cookie_accept": "#onetrust-accept-btn-handler, button:has-text('Accept All Cookies')",
    "cookie_settings_close": "#onetrust-pc-sdk button.onetrust-close-btn-handler, #onetrust-pc-sdk button[aria-label='Close']",
    "location_deny": "button:has-text('Never allow'), button:has-text('Block')",
    "extension_dismiss": "button[aria-label='Close'], button[aria-label='Dismiss']",
    "user_profile": "#user-profile",
    "shipping_history": "span.main-text:text-is('Shipping History'), a:has-text('Shipping History')",
    "date_range_modify": "#dateRangeModify",
    "history_date_range": "#nwsHistoryDateRangeDropdown",
    "date_range_apply": "#dateRangeApply",
    "calendar_start": ".ups-icon-calendar",
    "results_per_page": "#-resultsPerPage, select[name='resultsPerPage']",
    "history_table_row": "tbody tr:has(.ups-icon-ellipses)",
    "action_void": "#action_void",
    "void_yes": "#nbsVoidShipmentModalYes",
    "void_close": "#nbsVoidShipmentConfirmationModalClose",
    "pagination_next": "button:has(span:text-is('Next')), a:has(span:text-is('Next'))"
  },
  "void": {
    "history_url": "https://www.ups.com/ship/history?loc=en_US"
  },
  "timing": {
    "verify_wait_ms": 8000,
    "after_login_ms": 2000,
    "login_type_delay_ms": 100,
    "before_login_continue_ms": 1500,
    "after_login_continue_ms": 2500,
    "after_upload_ms": 3000,
    "after_process_all_ms": 45000,
    "post_void_browser_wait_s": 120,
    "after_history_filter_ms": 3000,
    "history_page_ms": 2500,
    "between_void_ms": 600,
    "micro_pause_ms": 400,
    "popup_wait_ms": 1800,
    "popup_dismiss_rounds": 4
  }
}
